{
  "project_info": {
    "project_number": "942870076780",
    "project_id": "gobelins-bombastic-manager",
    "storage_bucket": "gobelins-bombastic-manager.appspot.com"
  },
  "client": [
    {
      "client_info": {
        "mobilesdk_app_id": "1:942870076780:android:e082da14f35b0da4ea6749",
        "android_client_info": {
          "package_name": "com.bombastic.pocmultiplayer"
        }
      },
      "oauth_client": [],
      "api_key": [
        {
          "current_key": "AIzaSyAMQTNoY0x6ZMs4WGyFcjvU5qNAEQgOfLc"
        }
      ],
      "services": {
        "appinvite_service": {
          "other_platform_oauth_client": []
        }
      }
    }
  ],
  "configuration_version": "1"
}